agl_base_db/__init__.py
agl_base_db/admin.py
agl_base_db/apps.py
agl_base_db/data/__init__.py
agl_base_db/data/active_model/data.yaml
agl_base_db/data/center/data.yaml
agl_base_db/data/endoscope_type/data.yaml
agl_base_db/data/endoscopy_processor/data.yaml
agl_base_db/data/examination/examinations/data.yaml
agl_base_db/data/examination/time/data.yaml
agl_base_db/data/examination/time-type/data.yaml
agl_base_db/data/examination/type/data.yaml
agl_base_db/data/information_source/data.yaml
agl_base_db/data/label/label/data.yaml
agl_base_db/data/label/label-set/data.yaml
agl_base_db/data/label/label-type/data.yaml
agl_base_db/data/model_type/data.yaml
agl_base_db/data/profession/data.yaml
agl_base_db/data/unit/data.yaml
agl_base_db/data/unit/length.yaml
agl_base_db/data/unit/volume.yaml
agl_base_db/data/unit/weight.yaml
agl_base_db/forms/__init__.py
agl_base_db/forms/settings/__init__.py
agl_base_db/forms/unit.py
agl_base_db/management/commands/_load_model_template.py
agl_base_db/management/commands/delete_legacy_images.py
agl_base_db/management/commands/delete_legacy_videos.py
agl_base_db/management/commands/extract_legacy_video_frames.py
agl_base_db/management/commands/fetch_legacy_image_dataset.py
agl_base_db/management/commands/import_legacy_images.py
agl_base_db/management/commands/import_legacy_videos.py
agl_base_db/management/commands/load_active_model_data.py
agl_base_db/management/commands/load_ai_model_data.py
agl_base_db/management/commands/load_base_db_data.py
agl_base_db/management/commands/load_center_data.py
agl_base_db/management/commands/load_endoscope_type_data.py
agl_base_db/management/commands/load_endoscopy_processor_data.py
agl_base_db/management/commands/load_examination_data.py
agl_base_db/management/commands/load_information_source.py
agl_base_db/management/commands/load_label_data.py
agl_base_db/management/commands/load_profession_data.py
agl_base_db/management/commands/load_unit_data.py
agl_base_db/management/commands/load_user_groups.py
agl_base_db-0.1.54.dist-info/LICENSE
agl_base_db-0.1.54.dist-info/METADATA
agl_base_db-0.1.54.dist-info/WHEEL
agl_base_db-0.1.54.dist-info/RECORD
