Metadata-Version: 2.1
Name: agl-base-db
Version: 0.1.54
Summary: Basic shared components for the django based database of our workgroup.
License: MIT
Author: Thomas J. Lux
Requires-Python: >3.10,<3.13
Classifier: License :: OSI Approved :: MIT License
Classifier: Programming Language :: Python :: 3
Classifier: Programming Language :: Python :: 3.11
Requires-Dist: Django (>=5.0.1,<6.0.0)
Requires-Dist: agl-report-reader (>=0.1.3,<0.2.0)
Requires-Dist: django-extensions (>=3.2.3,<4.0.0)
Requires-Dist: djangorestframework (>=3.14.0,<4.0.0)
Requires-Dist: opencv-python (>=4.8.1.78,<5.0.0.0)
Requires-Dist: pytesseract (>=0.3.10,<0.4.0)
Requires-Dist: pyyaml (>=6.0.1,<7.0.0)
Requires-Dist: tqdm (>=4.66.1,<5.0.0)
